zeus_server_app/ViGEmBus_Setup_1.22.0.exe
zeus_server_app/__init__.py
zeus_server_app/__main__.py
zeus_server_app/chrome_manager.py
zeus_server_app/config_manager.py
zeus_server_app/gamepad_controller.py
zeus_server_app/hwid_manager.py
zeus_server_app/server.py
zeus_server_app/utils.py
zeus_server_app-1.0.17.dist-info/LICENSE
zeus_server_app-1.0.17.dist-info/METADATA
zeus_server_app-1.0.17.dist-info/WHEEL
zeus_server_app-1.0.17.dist-info/entry_points.txt
zeus_server_app-1.0.17.dist-info/top_level.txt
zeus_server_app-1.0.17.dist-info/RECORD
