Metadata-Version: 2.1
Name: zeus_server_app
Version: 1.0.17
Summary: A server for controlling gamepad inputs and managing HWIDs.
Home-page: https://github.com/satyajiit/zeus-server-load
Author: GamesPatch
Author-email: hello.theappstack@gmail.com
License: MIT
Classifier: Programming Language :: Python :: 3
Classifier: License :: OSI Approved :: MIT License
Classifier: Operating System :: Microsoft :: Windows
Classifier: Operating System :: POSIX :: Linux
Requires-Python: >=3.6
License-File: LICENSE
Requires-Dist: vgamepad
Requires-Dist: colorama
Requires-Dist: requests
